easierlog/__init__.py
easierlog/easierlog.py
easierlog/helpers.py
easierlog-1.1.1.dist-info/LICENSE
easierlog-1.1.1.dist-info/METADATA
easierlog-1.1.1.dist-info/WHEEL
easierlog-1.1.1.dist-info/top_level.txt
easierlog-1.1.1.dist-info/RECORD
