Metadata-Version: 2.1
Name: easierlog
Version: 1.1.1
Summary: The easy way to inspect variables in Python
Home-page: https://github.com/dilsonlira/easierlog
Author: Manoel Lira
Author-email: dilsonlira@gmail.com
License: MIT
Platform: UNKNOWN
Classifier: License :: OSI Approved :: MIT License
Classifier: Programming Language :: Python :: 3
Classifier: Programming Language :: Python :: 3.6
Classifier: Programming Language :: Python :: 3.7
Classifier: Programming Language :: Python :: 3.8
Classifier: Programming Language :: Python :: 3.9
Requires-Python: >=3.6.0
